semiphemeral/__init__.py
semiphemeral/common.py
semiphemeral/db.py
semiphemeral/import_export.py
semiphemeral/settings.py
semiphemeral/twitter.py
semiphemeral/web.py
semiphemeral/static/style.css
semiphemeral/static/img/loading.gif
semiphemeral/static/js/base.js
semiphemeral/static/js/settings.js
semiphemeral/static/js/tweets.js
semiphemeral/static/js/lib/jquery-3.4.1.min.js
semiphemeral/templates/base.html
semiphemeral/templates/settings.html
semiphemeral/templates/tweets.html
semiphemeral-0.7.dist-info/LICENSE
semiphemeral-0.7.dist-info/METADATA
semiphemeral-0.7.dist-info/WHEEL
semiphemeral-0.7.dist-info/entry_points.txt
semiphemeral-0.7.dist-info/top_level.txt
semiphemeral-0.7.dist-info/RECORD
