Metadata-Version: 2.1
Name: semiphemeral
Version: 0.7
Summary: Automatically delete your old tweets, except for the ones you want to keep
Home-page: https://github.com/micahflee/semiphemeral
Author: Micah Lee
Author-email: micah@micahflee.com
License: MIT
Platform: UNKNOWN
Classifier: Development Status :: 2 - Pre-Alpha
Classifier: Environment :: Console
Classifier: Intended Audience :: End Users/Desktop
Classifier: License :: OSI Approved :: MIT License
License-File: LICENSE
Requires-Dist: click
Requires-Dist: colorama
Requires-Dist: tweepy
Requires-Dist: flask
Requires-Dist: sqlalchemy
